<?xml version="1.0" encoding="UTF-8"?>
<?xml-stylesheet href="CoreNLP-to-HTML.xsl" type="text/xsl"?>
<root>
  <document>
    <sentences>
      <sentence id="1">
        <tokens>
          <token id="1">
            <word>No</word>
            <lemma>no</lemma>
            <CharacterOffsetBegin>0</CharacterOffsetBegin>
            <CharacterOffsetEnd>2</CharacterOffsetEnd>
            <POS>DT</POS>
            <NER>O</NER>
            <Speaker>PER0</Speaker>
            <TrueCase>O</TrueCase>
            <TrueCaseText>No</TrueCaseText>
          </token>
          <token id="2">
            <word>crooked</word>
            <lemma>crooked</lemma>
            <CharacterOffsetBegin>3</CharacterOffsetBegin>
            <CharacterOffsetEnd>10</CharacterOffsetEnd>
            <POS>JJ</POS>
            <NER>O</NER>
            <Speaker>PER0</Speaker>
            <TrueCase>LOWER</TrueCase>
            <TrueCaseText>crooked</TrueCaseText>
          </token>
          <token id="3">
            <word>leg</word>
            <lemma>leg</lemma>
            <CharacterOffsetBegin>11</CharacterOffsetBegin>
            <CharacterOffsetEnd>14</CharacterOffsetEnd>
            <POS>NN</POS>
            <NER>O</NER>
            <Speaker>PER0</Speaker>
            <TrueCase>LOWER</TrueCase>
            <TrueCaseText>leg</TrueCaseText>
          </token>
          <token id="4">
            <word>,</word>
            <lemma>,</lemma>
            <CharacterOffsetBegin>14</CharacterOffsetBegin>
            <CharacterOffsetEnd>15</CharacterOffsetEnd>
            <POS>,</POS>
            <NER>O</NER>
            <Speaker>PER0</Speaker>
            <TrueCase>O</TrueCase>
            <TrueCaseText>,</TrueCaseText>
          </token>
          <token id="5">
            <word>no</word>
            <lemma>no</lemma>
            <CharacterOffsetBegin>16</CharacterOffsetBegin>
            <CharacterOffsetEnd>18</CharacterOffsetEnd>
            <POS>DT</POS>
            <NER>O</NER>
            <Speaker>PER0</Speaker>
            <TrueCase>LOWER</TrueCase>
            <TrueCaseText>no</TrueCaseText>
          </token>
          <token id="6">
            <word>bleared</word>
            <lemma>bleared</lemma>
            <CharacterOffsetBegin>19</CharacterOffsetBegin>
            <CharacterOffsetEnd>26</CharacterOffsetEnd>
            <POS>JJ</POS>
            <NER>O</NER>
            <Speaker>PER0</Speaker>
            <TrueCase>LOWER</TrueCase>
            <TrueCaseText>bleared</TrueCaseText>
          </token>
          <token id="7">
            <word>eye</word>
            <lemma>eye</lemma>
            <CharacterOffsetBegin>27</CharacterOffsetBegin>
            <CharacterOffsetEnd>30</CharacterOffsetEnd>
            <POS>NN</POS>
            <NER>O</NER>
            <Speaker>PER0</Speaker>
            <TrueCase>LOWER</TrueCase>
            <TrueCaseText>eye</TrueCaseText>
          </token>
          <token id="8">
            <word>,</word>
            <lemma>,</lemma>
            <CharacterOffsetBegin>30</CharacterOffsetBegin>
            <CharacterOffsetEnd>31</CharacterOffsetEnd>
            <POS>,</POS>
            <NER>O</NER>
            <Speaker>PER0</Speaker>
            <TrueCase>O</TrueCase>
            <TrueCaseText>,</TrueCaseText>
          </token>
          <token id="9">
            <word>No</word>
            <lemma>no</lemma>
            <CharacterOffsetBegin>33</CharacterOffsetBegin>
            <CharacterOffsetEnd>35</CharacterOffsetEnd>
            <POS>DT</POS>
            <NER>O</NER>
            <Speaker>PER0</Speaker>
            <TrueCase>LOWER</TrueCase>
            <TrueCaseText>no</TrueCaseText>
          </token>
          <token id="10">
            <word>part</word>
            <lemma>part</lemma>
            <CharacterOffsetBegin>36</CharacterOffsetBegin>
            <CharacterOffsetEnd>40</CharacterOffsetEnd>
            <POS>NN</POS>
            <NER>O</NER>
            <Speaker>PER0</Speaker>
            <TrueCase>LOWER</TrueCase>
            <TrueCaseText>part</TrueCaseText>
          </token>
          <token id="11">
            <word>deformed</word>
            <lemma>deform</lemma>
            <CharacterOffsetBegin>41</CharacterOffsetBegin>
            <CharacterOffsetEnd>49</CharacterOffsetEnd>
            <POS>VBN</POS>
            <NER>O</NER>
            <Speaker>PER0</Speaker>
            <TrueCase>LOWER</TrueCase>
            <TrueCaseText>deformed</TrueCaseText>
          </token>
          <token id="12">
            <word>out</word>
            <lemma>out</lemma>
            <CharacterOffsetBegin>50</CharacterOffsetBegin>
            <CharacterOffsetEnd>53</CharacterOffsetEnd>
            <POS>IN</POS>
            <NER>O</NER>
            <Speaker>PER0</Speaker>
            <TrueCase>LOWER</TrueCase>
            <TrueCaseText>out</TrueCaseText>
          </token>
          <token id="13">
            <word>of</word>
            <lemma>of</lemma>
            <CharacterOffsetBegin>54</CharacterOffsetBegin>
            <CharacterOffsetEnd>56</CharacterOffsetEnd>
            <POS>IN</POS>
            <NER>O</NER>
            <Speaker>PER0</Speaker>
            <TrueCase>LOWER</TrueCase>
            <TrueCaseText>of</TrueCaseText>
          </token>
          <token id="14">
            <word>kind</word>
            <lemma>kind</lemma>
            <CharacterOffsetBegin>57</CharacterOffsetBegin>
            <CharacterOffsetEnd>61</CharacterOffsetEnd>
            <POS>NN</POS>
            <NER>O</NER>
            <Speaker>PER0</Speaker>
            <TrueCase>LOWER</TrueCase>
            <TrueCaseText>kind</TrueCaseText>
          </token>
          <token id="15">
            <word>,</word>
            <lemma>,</lemma>
            <CharacterOffsetBegin>61</CharacterOffsetBegin>
            <CharacterOffsetEnd>62</CharacterOffsetEnd>
            <POS>,</POS>
            <NER>O</NER>
            <Speaker>PER0</Speaker>
            <TrueCase>O</TrueCase>
            <TrueCaseText>,</TrueCaseText>
          </token>
          <token id="16">
            <word>Nor</word>
            <lemma>nor</lemma>
            <CharacterOffsetBegin>64</CharacterOffsetBegin>
            <CharacterOffsetEnd>67</CharacterOffsetEnd>
            <POS>CC</POS>
            <NER>O</NER>
            <Speaker>PER0</Speaker>
            <TrueCase>LOWER</TrueCase>
            <TrueCaseText>nor</TrueCaseText>
          </token>
          <token id="17">
            <word>yet</word>
            <lemma>yet</lemma>
            <CharacterOffsetBegin>68</CharacterOffsetBegin>
            <CharacterOffsetEnd>71</CharacterOffsetEnd>
            <POS>RB</POS>
            <NER>O</NER>
            <Speaker>PER0</Speaker>
            <TrueCase>LOWER</TrueCase>
            <TrueCaseText>yet</TrueCaseText>
          </token>
          <token id="18">
            <word>so</word>
            <lemma>so</lemma>
            <CharacterOffsetBegin>72</CharacterOffsetBegin>
            <CharacterOffsetEnd>74</CharacterOffsetEnd>
            <POS>RB</POS>
            <NER>O</NER>
            <Speaker>PER0</Speaker>
            <TrueCase>LOWER</TrueCase>
            <TrueCaseText>so</TrueCaseText>
          </token>
          <token id="19">
            <word>ugly</word>
            <lemma>ugly</lemma>
            <CharacterOffsetBegin>75</CharacterOffsetBegin>
            <CharacterOffsetEnd>79</CharacterOffsetEnd>
            <POS>JJ</POS>
            <NER>O</NER>
            <Speaker>PER0</Speaker>
            <TrueCase>LOWER</TrueCase>
            <TrueCaseText>ugly</TrueCaseText>
          </token>
          <token id="20">
            <word>half</word>
            <lemma>half</lemma>
            <CharacterOffsetBegin>80</CharacterOffsetBegin>
            <CharacterOffsetEnd>84</CharacterOffsetEnd>
            <POS>NN</POS>
            <NER>O</NER>
            <Speaker>PER0</Speaker>
            <TrueCase>LOWER</TrueCase>
            <TrueCaseText>half</TrueCaseText>
          </token>
          <token id="21">
            <word>can</word>
            <lemma>can</lemma>
            <CharacterOffsetBegin>85</CharacterOffsetBegin>
            <CharacterOffsetEnd>88</CharacterOffsetEnd>
            <POS>MD</POS>
            <NER>O</NER>
            <Speaker>PER0</Speaker>
            <TrueCase>LOWER</TrueCase>
            <TrueCaseText>can</TrueCaseText>
          </token>
          <token id="22">
            <word>be</word>
            <lemma>be</lemma>
            <CharacterOffsetBegin>89</CharacterOffsetBegin>
            <CharacterOffsetEnd>91</CharacterOffsetEnd>
            <POS>VB</POS>
            <NER>O</NER>
            <Speaker>PER0</Speaker>
            <TrueCase>LOWER</TrueCase>
            <TrueCaseText>be</TrueCaseText>
          </token>
          <token id="23">
            <word>As</word>
            <lemma>as</lemma>
            <CharacterOffsetBegin>93</CharacterOffsetBegin>
            <CharacterOffsetEnd>95</CharacterOffsetEnd>
            <POS>RB</POS>
            <NER>O</NER>
            <Speaker>PER0</Speaker>
            <TrueCase>O</TrueCase>
            <TrueCaseText>As</TrueCaseText>
          </token>
          <token id="24">
            <word>is</word>
            <lemma>be</lemma>
            <CharacterOffsetBegin>96</CharacterOffsetBegin>
            <CharacterOffsetEnd>98</CharacterOffsetEnd>
            <POS>VBZ</POS>
            <NER>O</NER>
            <Speaker>PER0</Speaker>
            <TrueCase>LOWER</TrueCase>
            <TrueCaseText>is</TrueCaseText>
          </token>
          <token id="25">
            <word>the</word>
            <lemma>the</lemma>
            <CharacterOffsetBegin>99</CharacterOffsetBegin>
            <CharacterOffsetEnd>102</CharacterOffsetEnd>
            <POS>DT</POS>
            <NER>O</NER>
            <Speaker>PER0</Speaker>
            <TrueCase>LOWER</TrueCase>
            <TrueCaseText>the</TrueCaseText>
          </token>
          <token id="26">
            <word>inward</word>
            <lemma>inward</lemma>
            <CharacterOffsetBegin>103</CharacterOffsetBegin>
            <CharacterOffsetEnd>109</CharacterOffsetEnd>
            <POS>JJ</POS>
            <NER>O</NER>
            <Speaker>PER0</Speaker>
            <TrueCase>LOWER</TrueCase>
            <TrueCaseText>inward</TrueCaseText>
          </token>
          <token id="27">
            <word>suspicious</word>
            <lemma>suspicious</lemma>
            <CharacterOffsetBegin>110</CharacterOffsetBegin>
            <CharacterOffsetEnd>120</CharacterOffsetEnd>
            <POS>JJ</POS>
            <NER>O</NER>
            <Speaker>PER0</Speaker>
            <TrueCase>LOWER</TrueCase>
            <TrueCaseText>suspicious</TrueCaseText>
          </token>
          <token id="28">
            <word>mind</word>
            <lemma>mind</lemma>
            <CharacterOffsetBegin>121</CharacterOffsetBegin>
            <CharacterOffsetEnd>125</CharacterOffsetEnd>
            <POS>NN</POS>
            <NER>O</NER>
            <Speaker>PER0</Speaker>
            <TrueCase>LOWER</TrueCase>
            <TrueCaseText>mind</TrueCaseText>
          </token>
          <token id="29">
            <word>.</word>
            <lemma>.</lemma>
            <CharacterOffsetBegin>125</CharacterOffsetBegin>
            <CharacterOffsetEnd>126</CharacterOffsetEnd>
            <POS>.</POS>
            <NER>O</NER>
            <Speaker>PER0</Speaker>
            <TrueCase>O</TrueCase>
            <TrueCaseText>.</TrueCaseText>
          </token>
        </tokens>
        <parse>(ROOT (NP (NP (DT No) (JJ crooked) (NN leg)) (, ,) (NP (DT no) (JJ bleared) (NN eye)) (, ,) (S (S (NP (DT No) (NN part)) (ADJP (VBN deformed) (PP (IN out) (PP (IN of) (NP (NN kind)))))) (, ,) (CC Nor) (S (ADVP (RB yet)) (NP (ADJP (RB so) (JJ ugly)) (NN half)) (VP (MD can) (VP (VB be) (ADVP (RB As) (S (VP (VBZ is) (NP (DT the) (ADJP (JJ inward) (JJ suspicious)) (NN mind))))))))) (. .))) </parse>
        <dependencies type="basic-dependencies">
          <dep type="root">
            <governor idx="0">ROOT</governor>
            <dependent idx="3">leg</dependent>
          </dep>
          <dep type="neg">
            <governor idx="3">leg</governor>
            <dependent idx="1">No</dependent>
          </dep>
          <dep type="amod">
            <governor idx="3">leg</governor>
            <dependent idx="2">crooked</dependent>
          </dep>
          <dep type="neg">
            <governor idx="7">eye</governor>
            <dependent idx="5">no</dependent>
          </dep>
          <dep type="amod">
            <governor idx="7">eye</governor>
            <dependent idx="6">bleared</dependent>
          </dep>
          <dep type="appos">
            <governor idx="3">leg</governor>
            <dependent idx="7">eye</dependent>
          </dep>
          <dep type="neg">
            <governor idx="10">part</governor>
            <dependent idx="9">No</dependent>
          </dep>
          <dep type="dep">
            <governor idx="11">deformed</governor>
            <dependent idx="10">part</dependent>
          </dep>
          <dep type="dep">
            <governor idx="3">leg</governor>
            <dependent idx="11">deformed</dependent>
          </dep>
          <dep type="prep">
            <governor idx="11">deformed</governor>
            <dependent idx="12">out</dependent>
          </dep>
          <dep type="pcomp">
            <governor idx="12">out</governor>
            <dependent idx="13">of</dependent>
          </dep>
          <dep type="pobj">
            <governor idx="13">of</governor>
            <dependent idx="14">kind</dependent>
          </dep>
          <dep type="cc">
            <governor idx="11">deformed</governor>
            <dependent idx="16">Nor</dependent>
          </dep>
          <dep type="advmod">
            <governor idx="22">be</governor>
            <dependent idx="17">yet</dependent>
          </dep>
          <dep type="advmod">
            <governor idx="19">ugly</governor>
            <dependent idx="18">so</dependent>
          </dep>
          <dep type="amod">
            <governor idx="20">half</governor>
            <dependent idx="19">ugly</dependent>
          </dep>
          <dep type="nsubj">
            <governor idx="22">be</governor>
            <dependent idx="20">half</dependent>
          </dep>
          <dep type="aux">
            <governor idx="22">be</governor>
            <dependent idx="21">can</dependent>
          </dep>
          <dep type="conj">
            <governor idx="11">deformed</governor>
            <dependent idx="22">be</dependent>
          </dep>
          <dep type="advmod">
            <governor idx="22">be</governor>
            <dependent idx="23">As</dependent>
          </dep>
          <dep type="cop">
            <governor idx="28">mind</governor>
            <dependent idx="24">is</dependent>
          </dep>
          <dep type="det">
            <governor idx="28">mind</governor>
            <dependent idx="25">the</dependent>
          </dep>
          <dep type="amod">
            <governor idx="27">suspicious</governor>
            <dependent idx="26">inward</dependent>
          </dep>
          <dep type="amod">
            <governor idx="28">mind</governor>
            <dependent idx="27">suspicious</dependent>
          </dep>
          <dep type="dep">
            <governor idx="23">As</governor>
            <dependent idx="28">mind</dependent>
          </dep>
        </dependencies>
        <dependencies type="collapsed-dependencies">
          <dep type="root">
            <governor idx="0">ROOT</governor>
            <dependent idx="3">leg</dependent>
          </dep>
          <dep type="neg">
            <governor idx="3">leg</governor>
            <dependent idx="1">No</dependent>
          </dep>
          <dep type="amod">
            <governor idx="3">leg</governor>
            <dependent idx="2">crooked</dependent>
          </dep>
          <dep type="neg">
            <governor idx="7">eye</governor>
            <dependent idx="5">no</dependent>
          </dep>
          <dep type="amod">
            <governor idx="7">eye</governor>
            <dependent idx="6">bleared</dependent>
          </dep>
          <dep type="appos">
            <governor idx="3">leg</governor>
            <dependent idx="7">eye</dependent>
          </dep>
          <dep type="neg">
            <governor idx="10">part</governor>
            <dependent idx="9">No</dependent>
          </dep>
          <dep type="dep">
            <governor idx="11">deformed</governor>
            <dependent idx="10">part</dependent>
          </dep>
          <dep type="dep">
            <governor idx="3">leg</governor>
            <dependent idx="11">deformed</dependent>
          </dep>
          <dep type="prepc_out_of">
            <governor idx="11">deformed</governor>
            <dependent idx="13">of</dependent>
          </dep>
          <dep type="pobj">
            <governor idx="11">deformed</governor>
            <dependent idx="14">kind</dependent>
          </dep>
          <dep type="advmod">
            <governor idx="22">be</governor>
            <dependent idx="17">yet</dependent>
          </dep>
          <dep type="advmod">
            <governor idx="19">ugly</governor>
            <dependent idx="18">so</dependent>
          </dep>
          <dep type="amod">
            <governor idx="20">half</governor>
            <dependent idx="19">ugly</dependent>
          </dep>
          <dep type="nsubj">
            <governor idx="22">be</governor>
            <dependent idx="20">half</dependent>
          </dep>
          <dep type="aux">
            <governor idx="22">be</governor>
            <dependent idx="21">can</dependent>
          </dep>
          <dep type="conj_nor">
            <governor idx="11">deformed</governor>
            <dependent idx="22">be</dependent>
          </dep>
          <dep type="advmod">
            <governor idx="22">be</governor>
            <dependent idx="23">As</dependent>
          </dep>
          <dep type="cop">
            <governor idx="28">mind</governor>
            <dependent idx="24">is</dependent>
          </dep>
          <dep type="det">
            <governor idx="28">mind</governor>
            <dependent idx="25">the</dependent>
          </dep>
          <dep type="amod">
            <governor idx="27">suspicious</governor>
            <dependent idx="26">inward</dependent>
          </dep>
          <dep type="amod">
            <governor idx="28">mind</governor>
            <dependent idx="27">suspicious</dependent>
          </dep>
          <dep type="dep">
            <governor idx="23">As</governor>
            <dependent idx="28">mind</dependent>
          </dep>
        </dependencies>
        <dependencies type="collapsed-ccprocessed-dependencies">
          <dep type="root">
            <governor idx="0">ROOT</governor>
            <dependent idx="3">leg</dependent>
          </dep>
          <dep type="neg">
            <governor idx="3">leg</governor>
            <dependent idx="1">No</dependent>
          </dep>
          <dep type="amod">
            <governor idx="3">leg</governor>
            <dependent idx="2">crooked</dependent>
          </dep>
          <dep type="neg">
            <governor idx="7">eye</governor>
            <dependent idx="5">no</dependent>
          </dep>
          <dep type="amod">
            <governor idx="7">eye</governor>
            <dependent idx="6">bleared</dependent>
          </dep>
          <dep type="appos">
            <governor idx="3">leg</governor>
            <dependent idx="7">eye</dependent>
          </dep>
          <dep type="neg">
            <governor idx="10">part</governor>
            <dependent idx="9">No</dependent>
          </dep>
          <dep type="dep">
            <governor idx="11">deformed</governor>
            <dependent idx="10">part</dependent>
          </dep>
          <dep type="dep">
            <governor idx="3">leg</governor>
            <dependent idx="11">deformed</dependent>
          </dep>
          <dep type="prepc_out_of">
            <governor idx="11">deformed</governor>
            <dependent idx="13">of</dependent>
          </dep>
          <dep type="pobj">
            <governor idx="11">deformed</governor>
            <dependent idx="14">kind</dependent>
          </dep>
          <dep type="advmod">
            <governor idx="22">be</governor>
            <dependent idx="17">yet</dependent>
          </dep>
          <dep type="advmod">
            <governor idx="19">ugly</governor>
            <dependent idx="18">so</dependent>
          </dep>
          <dep type="amod">
            <governor idx="20">half</governor>
            <dependent idx="19">ugly</dependent>
          </dep>
          <dep type="nsubj">
            <governor idx="22">be</governor>
            <dependent idx="20">half</dependent>
          </dep>
          <dep type="aux">
            <governor idx="22">be</governor>
            <dependent idx="21">can</dependent>
          </dep>
          <dep type="dep">
            <governor idx="3">leg</governor>
            <dependent idx="22">be</dependent>
          </dep>
          <dep type="conj_nor">
            <governor idx="11">deformed</governor>
            <dependent idx="22">be</dependent>
          </dep>
          <dep type="advmod">
            <governor idx="22">be</governor>
            <dependent idx="23">As</dependent>
          </dep>
          <dep type="cop">
            <governor idx="28">mind</governor>
            <dependent idx="24">is</dependent>
          </dep>
          <dep type="det">
            <governor idx="28">mind</governor>
            <dependent idx="25">the</dependent>
          </dep>
          <dep type="amod">
            <governor idx="27">suspicious</governor>
            <dependent idx="26">inward</dependent>
          </dep>
          <dep type="amod">
            <governor idx="28">mind</governor>
            <dependent idx="27">suspicious</dependent>
          </dep>
          <dep type="dep">
            <governor idx="23">As</governor>
            <dependent idx="28">mind</dependent>
          </dep>
        </dependencies>
      </sentence>
    </sentences>
    <coreference>
      <coreference>
        <mention representative="true">
          <sentence>1</sentence>
          <start>1</start>
          <end>4</end>
          <head>3</head>
          <text>No crooked leg</text>
        </mention>
        <mention>
          <sentence>1</sentence>
          <start>5</start>
          <end>8</end>
          <head>7</head>
          <text>no bleared eye</text>
        </mention>
      </coreference>
    </coreference>
  </document>
</root>
